websub/__init__.py
websub_temporary-0.0.4.dist-info/LICENSE
websub_temporary-0.0.4.dist-info/WHEEL
websub_temporary-0.0.4.dist-info/METADATA
websub_temporary-0.0.4.dist-info/RECORD
